{
  "name": "acf/contact-form",
  "title": "Contact formulier",
  "category": "sections",
  "icon": "phone",
  "keywords": ["contact", "form"],
  "acf": {
      "mode": "preview"
  },
  "supports": {
      "anchor": true,
      "jsx": true,
      "align": [ "full", "wide" ],
      "fullHeight": false,
      "alignText": false,
      "spacing": {
          "margin": [
              "top",
              "bottom"
          ],
          "padding": [
              "top",
              "bottom"
          ]
      },
      "color": {
          "background": true,
          "text": true
      }
  },
  "attributes": {
      "style": {
          "type": "object",
          "default" : {
              "spacing":
              {
                  "padding": {
                      "top": "80px",
                      "bottom": "80px"
                  }
              }
          }
      }
  }
}
